PrakashBasicCalculator/__init__.py
PrakashBasicCalculator-0.0.1.dist-info/LICENSE.txt
PrakashBasicCalculator-0.0.1.dist-info/METADATA
PrakashBasicCalculator-0.0.1.dist-info/WHEEL
PrakashBasicCalculator-0.0.1.dist-info/top_level.txt
PrakashBasicCalculator-0.0.1.dist-info/RECORD
