Metadata-Version: 2.1
Name: PrakashBasicCalculator
Version: 0.0.1
Summary: A Basic Python Package for Calculations.
Author: Krishna Prakash
Author-email: krishnaprakash603@gmail.com
Classifier: Programming Language :: Python :: 3
Classifier: License :: OSI Approved :: MIT License
Classifier: Operating System :: OS Independent
License-File: LICENSE.txt
